desktop_api/__init__.py
desktop_api/__version__.py
desktop_api/actions.py
desktop_api/capture.py
desktop_api/controller.py
desktop_api/window.py
desktop_api-0.2.0.dist-info/METADATA
desktop_api-0.2.0.dist-info/WHEEL
desktop_api-0.2.0.dist-info/top_level.txt
desktop_api-0.2.0.dist-info/RECORD
