Metadata-Version: 2.4
Name: desktop-api
Version: 0.2.0
Summary: Cross-platform desktop automation API for capturing windows and performing GUI actions
Author-email: Denis Karachev <welcomedenk@gmail.com>
Project-URL: Homepage, https://github.com/thedenk/desktop-api
Project-URL: Repository, https://github.com/thedenk/desktop-api
Keywords: desktop,automation,gui,screenshot,screen-capture
Classifier: Programming Language :: Python :: 3
Classifier: Programming Language :: Python :: 3 :: Only
Classifier: Programming Language :: Python :: 3.9
Classifier: Programming Language :: Python :: 3.10
Classifier: Programming Language :: Python :: 3.11
Classifier: Programming Language :: Python :: 3.12
Classifier: Operating System :: MacOS :: MacOS X
Classifier: Operating System :: Microsoft :: Windows
Classifier: Operating System :: POSIX :: Linux
Requires-Python: >=3.9
Requires-Dist: pyautogui>=0.9.54
Requires-Dist: pygetwindow>=0.0.9
Requires-Dist: mss>=9.0.1
Requires-Dist: Pillow>=10.0.0
Requires-Dist: python-xlib>=0.33; platform_system == "Linux"
Provides-Extra: dev
Requires-Dist: black>=24.3; extra == "dev"
Requires-Dist: ruff>=0.1; extra == "dev"
Requires-Dist: pytest>=7.0.0; extra == "dev"
Provides-Extra: mac
Requires-Dist: pyobjc-core>=12.0; extra == "mac"
Requires-Dist: pyobjc-framework-Cocoa>=12.0; extra == "mac"
Requires-Dist: pyobjc-framework-Quartz>=12.0; extra == "mac"
Provides-Extra: unicode
Requires-Dist: pyperclip>=1.8.2; extra == "unicode"
